g2p_id/__init__.py
g2p_id/bert_pron.onnx
g2p_id/g2p.py
g2p_id/syllable_splitter.py
g2p_id/tiny-pron.onnx
g2p_id/data/dict.json
g2p_id/data/map.json
g2p_id-0.0.4.dist-info/LICENSE
g2p_id-0.0.4.dist-info/METADATA
g2p_id-0.0.4.dist-info/WHEEL
g2p_id-0.0.4.dist-info/top_level.txt
g2p_id-0.0.4.dist-info/RECORD
