Metadata-Version: 2.1
Name: g2p-id
Version: 0.0.4
Summary: Indonesian Grapheme-to-Phoneme (G2P)
Home-page: https://github.com/Wikidepia/g2p-id
Author: Akmal
Author-email: magchuz@pm.me
License: MIT
Classifier: Development Status :: 4 - Beta
Classifier: Intended Audience :: Developers
Classifier: License :: OSI Approved :: MIT License
Classifier: Programming Language :: Python :: 3.6
License-File: LICENSE
Requires-Dist: sacremoses (>=0.0.41)
Requires-Dist: numpy (>=1.22.4)
Requires-Dist: onnxruntime (>=1.11.1)
